sphinxcontrib_scalebybuilder-0.1.1-py3.8-nspkg.pth
sphinxcontrib/scalebybuilder.py
sphinxcontrib_scalebybuilder-0.1.1.dist-info/LICENSE.txt
sphinxcontrib_scalebybuilder-0.1.1.dist-info/METADATA
sphinxcontrib_scalebybuilder-0.1.1.dist-info/WHEEL
sphinxcontrib_scalebybuilder-0.1.1.dist-info/namespace_packages.txt
sphinxcontrib_scalebybuilder-0.1.1.dist-info/top_level.txt
sphinxcontrib_scalebybuilder-0.1.1.dist-info/RECORD
